fluffless/models/__init__.py
fluffless/models/base_model.py
fluffless/utils/__init__.py
fluffless/utils/cli.py
fluffless/utils/console.py
fluffless/utils/logging.py
fluffless-0.0.3.dist-info/licenses/LICENSE
fluffless-0.0.3.dist-info/METADATA
fluffless-0.0.3.dist-info/WHEEL
fluffless-0.0.3.dist-info/top_level.txt
fluffless-0.0.3.dist-info/RECORD
