Metadata-Version: 2.4
Name: fluffless
Version: 0.0.3
Summary: Simple, light Python framework for building CLI apps
Requires-Python: >=3.12
License-File: LICENSE
Requires-Dist: rich>=14.2.0
Requires-Dist: rich-argparse>=1.7.2
Provides-Extra: dev
Requires-Dist: actionlint-py>=1.7.9.24; extra == "dev"
Requires-Dist: flake8-assertive>=2.2.0; extra == "dev"
Requires-Dist: flake8-docstrings>=1.7.0; extra == "dev"
Requires-Dist: flake8-pyproject>=1.2.4; extra == "dev"
Requires-Dist: flake8>=7.3.0; extra == "dev"
Requires-Dist: pep8-naming>=0.15.1; extra == "dev"
Requires-Dist: pre-commit-hooks>=6.0.0; extra == "dev"
Requires-Dist: pre-commit>=4.5.0; extra == "dev"
Requires-Dist: pydoclint>=0.6.6; extra == "dev"
Requires-Dist: pytest-cov>=7.0.0; extra == "dev"
Requires-Dist: pytest>=9.0.2; extra == "dev"
Requires-Dist: ruff>=0.14.8; extra == "dev"
Requires-Dist: yamlfix>=1.17.0; extra == "dev"
Requires-Dist: zizmor>=1.11.0; extra == "dev"
Requires-Dist: ty>=0.0.1a32; extra == "dev"
Requires-Dist: zizmor>=1.18.0; extra == "dev"
Dynamic: license-file
